synthientpy/__init__.py
synthientpy/client.py
synthientpy/constants.py
synthientpy/exceptions.py
synthientpy/models.py
synthientpy/py.typed
synthientpy/utils.py
synthientpy-0.1.5.dist-info/LICENSE
synthientpy-0.1.5.dist-info/METADATA
synthientpy-0.1.5.dist-info/WHEEL
synthientpy-0.1.5.dist-info/RECORD
